{
  "users": [
    {
      "id": 5702702572,
      "idstr": "5702702572",
      "class": 1,
      "screen_name": "淡漠LCLED",
      "name": "淡漠LCLED",
      "province": "42",
      "city": "10",
      "location": "湖北 荆州",
      "description": "",
      "url": "",
      "profile_image_url": "https://tva1.sinaimg.cn/crop.0.0.200.200.50/006dVXrKjw8ewxiunw4qbj305k05kmx9.jpg?KID=imgbed,tva&Expires=1698852417&ssig=DMMBd9QecU",
      "light_ring": false,
      "profile_url": "u/5702702572",
      "domain": "",
      "weihao": "",
      "gender": "f",
      "followers_count": 39,
      "followers_count_str": "39",
      "friends_count": 454,
      "pagefriends_count": 0,
      "statuses_count": 20,
      "video_status_count": 0,
      "video_play_count": 0,
      "super_topic_not_syn_count": 0,
      "favourites_count": 0,
      "created_at": "Sun Sep 13 21:48:26 +0800 2015",
      "following": false,
      "allow_all_act_msg": false,
      "geo_enabled": true,
      "verified": false,
      "verified_type": -1,
      "remark": "",
      "insecurity": {
        "sexual_content": false
      },
      "status_id": 3974021726772763,
      "status_idstr": "3974021726772763",
      "ptype": 0,
      "allow_all_comment": true,
      "avatar_large": "https://tva1.sinaimg.cn/crop.0.0.200.200.180/006dVXrKjw8ewxiunw4qbj305k05kmx9.jpg?KID=imgbed,tva&Expires=1698852417&ssig=gTZ%2FHkidm%2F",
      "avatar_hd": "https://tva1.sinaimg.cn/crop.0.0.200.200.1024/006dVXrKjw8ewxiunw4qbj305k05kmx9.jpg?KID=imgbed,tva&Expires=1698852417&ssig=D6%2Fq%2FV8sNj",
      "verified_reason": "",
      "verified_trade": "",
      "verified_reason_url": "",
      "verified_source": "",
      "verified_source_url": "",
      "follow_me": false,
      "like": false,
      "like_me": false,
      "online_status": 0,
      "bi_followers_count": 29,
      "lang": "zh-cn",
      "star": 0,
      "mbtype": 0,
      "mbrank": 0,
      "svip": 0,
      "vvip": 0,
      "mb_expire_time": 0,
      "block_word": 0,
      "block_app": 0,
      "chaohua_ability": 0,
      "brand_ability": 0,
      "nft_ability": 0,
      "vplus_ability": 0,
      "wenda_ability": 0,
      "live_ability": 0,
      "gongyi_ability": 0,
      "paycolumn_ability": 0,
      "newbrand_ability": 0,
      "ecommerce_ability": 0,
      "hardfan_ability": 0,
      "wbcolumn_ability": 0,
      "interaction_user": 0,
      "audio_ability": 0,
      "credit_score": 80,
      "user_ability": 0,
      "urank": 5,
      "story_read_state": -1,
      "vclub_member": 0,
      "is_teenager": 0,
      "is_guardian": 0,
      "is_teenager_list": 0,
      "pc_new": 0,
      "special_follow": false,
      "planet_video": 0,
      "video_mark": 0,
      "live_status": 0,
      "user_ability_extend": 0,
      "status_total_counter": {
        "total_cnt": 8,
        "repost_cnt": 0,
        "comment_cnt": 1,
        "like_cnt": 7,
        "comment_like_cnt": 0
      },
      "video_total_counter": {
        "play_cnt": -1
      },
      "brand_account": 0,
      "hongbaofei": 0,
      "green_mode": 0,
      "urisk": 4398047035392,
      "unfollowing_recom_switch": 1,
      "block": 0,
      "block_me": 0,
      "avatar_type": 0,
      "is_big": 0,
      "auth_status": 0,
      "auth_realname": null,
      "auth_career": null,
      "auth_career_name": null,
      "show_auth": 0,
      "fansIcon": {
        "fans_uid": 5702702572,
        "val": 0,
        "member_rank": 0,
        "svip": 0,
        "vvip": 0,
        "lighting": false,
        "icon_url": "",
        "uid": 5702702572,
        "name": ""
      }
    },
    {
      "id": 3168261984,
      "idstr": "3168261984",
      "class": 1,
      "screen_name": "壹加壹云儿小叮当牛仔",
      "name": "壹加壹云儿小叮当牛仔",
      "province": "44",
      "city": "6",
      "location": "广东 佛山",
      "description": "",
      "url": "",
      "profile_image_url": "https://tva4.sinaimg.cn/crop.0.0.180.180.50/bcd7d760jw1e8qgp5bmzyj2050050aa8.jpg?KID=imgbed,tva&Expires=1698852417&ssig=FV%2BSZmsuCE",
      "light_ring": false,
      "profile_url": "u/3168261984",
      "domain": "",
      "weihao": "",
      "gender": "f",
      "followers_count": 25,
      "followers_count_str": "25",
      "friends_count": 252,
      "pagefriends_count": 0,
      "statuses_count": 261,
      "video_status_count": 0,
      "video_play_count": 0,
      "super_topic_not_syn_count": 0,
      "favourites_count": 0,
      "created_at": "Fri Jan 25 06:49:25 +0800 2013",
      "following": false,
      "allow_all_act_msg": false,
      "geo_enabled": true,
      "verified": false,
      "verified_type": -1,
      "remark": "",
      "insecurity": {
        "sexual_content": false
      },
      "status_id": 3992079871326269,
      "status_idstr": "3992079871326269",
      "ptype": 0,
      "allow_all_comment": true,
      "avatar_large": "https://tva4.sinaimg.cn/crop.0.0.180.180.180/bcd7d760jw1e8qgp5bmzyj2050050aa8.jpg?KID=imgbed,tva&Expires=1698852417&ssig=Pli%2BJCFmPL",
      "avatar_hd": "https://tva4.sinaimg.cn/crop.0.0.180.180.1024/bcd7d760jw1e8qgp5bmzyj2050050aa8.jpg?KID=imgbed,tva&Expires=1698852417&ssig=3xlH1coOAL",
      "verified_reason": "",
      "verified_trade": "",
      "verified_reason_url": "",
      "verified_source": "",
      "verified_source_url": "",
      "follow_me": false,
      "like": false,
      "like_me": false,
      "online_status": 0,
      "bi_followers_count": 9,
      "lang": "zh-cn",
      "star": 0,
      "mbtype": 0,
      "mbrank": 0,
      "svip": 0,
      "vvip": 0,
      "mb_expire_time": 0,
      "block_word": 0,
      "block_app": 0,
      "chaohua_ability": 0,
      "brand_ability": 0,
      "nft_ability": 0,
      "vplus_ability": 0,
      "wenda_ability": 0,
      "live_ability": 0,
      "gongyi_ability": 0,
      "paycolumn_ability": 0,
      "newbrand_ability": 0,
      "ecommerce_ability": 0,
      "hardfan_ability": 0,
      "wbcolumn_ability": 0,
      "interaction_user": 0,
      "audio_ability": 0,
      "credit_score": 80,
      "user_ability": 0,
      "urank": 14,
      "story_read_state": -1,
      "vclub_member": 0,
      "is_teenager": 0,
      "is_guardian": 0,
      "is_teenager_list": 0,
      "pc_new": 0,
      "special_follow": false,
      "planet_video": 0,
      "video_mark": 0,
      "live_status": 0,
      "user_ability_extend": 0,
      "status_total_counter": {
        "total_cnt": 16,
        "repost_cnt": 0,
        "comment_cnt": 15,
        "like_cnt": 1,
        "comment_like_cnt": 0
      },
      "video_total_counter": {
        "play_cnt": -1
      },
      "brand_account": 0,
      "hongbaofei": 0,
      "green_mode": 0,
      "urisk": 4398047035392,
      "unfollowing_recom_switch": 1,
      "block": 0,
      "block_me": 0,
      "avatar_type": 0,
      "is_big": 0,
      "auth_status": 0,
      "auth_realname": null,
      "auth_career": null,
      "auth_career_name": null,
      "show_auth": 0,
      "fansIcon": {
        "fans_uid": 3168261984,
        "val": 0,
        "member_rank": 0,
        "svip": 0,
        "vvip": 0,
        "lighting": false,
        "icon_url": "",
        "uid": 3168261984,
        "name": ""
      }
    },
    {
      "id": 2997981971,
      "idstr": "2997981971",
      "class": 1,
      "screen_name": "orchid315筹",
      "name": "orchid315筹",
      "province": "65",
      "city": "1000",
      "location": "新疆",
      "description": "",
      "url": "",
      "profile_image_url": "https://tva4.sinaimg.cn/crop.0.0.300.300.50/b2b19313jw1efxeu4wpa1j208c08cq2w.jpg?KID=imgbed,tva&Expires=1698852417&ssig=SGCCk3my4m",
      "light_ring": false,
      "profile_url": "u/2997981971",
      "domain": "",
      "weihao": "",
      "gender": "f",
      "followers_count": 340,
      "followers_count_str": "340",
      "friends_count": 1483,
      "pagefriends_count": 0,
      "statuses_count": 172,
      "video_status_count": 0,
      "video_play_count": 0,
      "super_topic_not_syn_count": 0,
      "favourites_count": 0,
      "created_at": "Thu Oct 25 10:45:04 +0800 2012",
      "following": false,
      "allow_all_act_msg": false,
      "geo_enabled": true,
      "verified": false,
      "verified_type": -1,
      "remark": "",
      "insecurity": {
        "sexual_content": false
      },
      "status_id": 3798087803860263,
      "status_idstr": "3798087803860263",
      "ptype": 0,
      "allow_all_comment": true,
      "avatar_large": "https://tva4.sinaimg.cn/crop.0.0.300.300.180/b2b19313jw1efxeu4wpa1j208c08cq2w.jpg?KID=imgbed,tva&Expires=1698852417&ssig=K0mVJ4dMuP",
      "avatar_hd": "https://tva4.sinaimg.cn/crop.0.0.300.300.1024/b2b19313jw1efxeu4wpa1j208c08cq2w.jpg?KID=imgbed,tva&Expires=1698852417&ssig=hgyLaP2AIz",
      "verified_reason": "",
      "verified_trade": "",
      "verified_reason_url": "",
      "verified_source": "",
      "verified_source_url": "",
      "follow_me": false,
      "like": false,
      "like_me": false,
      "online_status": 0,
      "bi_followers_count": 227,
      "lang": "zh-cn",
      "star": 0,
      "mbtype": 0,
      "mbrank": 0,
      "svip": 0,
      "vvip": 0,
      "mb_expire_time": 0,
      "block_word": 0,
      "block_app": 0,
      "chaohua_ability": 0,
      "brand_ability": 0,
      "nft_ability": 0,
      "vplus_ability": 0,
      "wenda_ability": 0,
      "live_ability": 0,
      "gongyi_ability": 0,
      "paycolumn_ability": 0,
      "newbrand_ability": 0,
      "ecommerce_ability": 0,
      "hardfan_ability": 0,
      "wbcolumn_ability": 0,
      "interaction_user": 0,
      "audio_ability": 0,
      "credit_score": 80,
      "user_ability": 0,
      "urank": 6,
      "story_read_state": -1,
      "vclub_member": 0,
      "is_teenager": 0,
      "is_guardian": 0,
      "is_teenager_list": 0,
      "pc_new": 0,
      "special_follow": false,
      "planet_video": 0,
      "video_mark": 0,
      "live_status": 0,
      "user_ability_extend": 0,
      "status_total_counter": {
        "total_cnt": 44,
        "repost_cnt": 0,
        "comment_cnt": 6,
        "like_cnt": 38,
        "comment_like_cnt": 0
      },
      "video_total_counter": {
        "play_cnt": -1
      },
      "brand_account": 0,
      "hongbaofei": 0,
      "green_mode": 0,
      "urisk": 4398047035392,
      "unfollowing_recom_switch": 1,
      "block": 0,
      "block_me": 0,
      "avatar_type": 0,
      "is_big": 0,
      "auth_status": 0,
      "auth_realname": null,
      "auth_career": null,
      "auth_career_name": null,
      "show_auth": 0,
      "fansIcon": {
        "fans_uid": 2997981971,
        "val": 0,
        "member_rank": 0,
        "svip": 0,
        "vvip": 0,
        "lighting": false,
        "icon_url": "",
        "uid": 2997981971,
        "name": ""
      }
    },
    {
      "id": 3900010641,
      "idstr": "3900010641",
      "class": 1,
      "screen_name": "洛小泊",
      "name": "洛小泊",
      "province": "82",
      "city": "1",
      "location": "澳门 其他",
      "description": "",
      "url": "",
      "profile_image_url": "https://tva4.sinaimg.cn/crop.0.20.160.160.50/e8757091jw1eak59nkesqj204g05kmxf.jpg?KID=imgbed,tva&Expires=1698852417&ssig=O3AKDCwkEu",
      "light_ring": false,
      "profile_url": "u/3900010641",
      "domain": "",
      "weihao": "",
      "gender": "m",
      "followers_count": 431,
      "followers_count_str": "431",
      "friends_count": 1579,
      "pagefriends_count": 0,
      "statuses_count": 7588,
      "video_status_count": 0,
      "video_play_count": 0,
      "super_topic_not_syn_count": 0,
      "favourites_count": 0,
      "created_at": "Mon Nov 11 16:38:33 +0800 2013",
      "following": false,
      "allow_all_act_msg": false,
      "geo_enabled": true,
      "verified": false,
      "verified_type": -1,
      "remark": "",
      "insecurity": {
        "sexual_content": false
      },
      "status_id": 3776204349960510,
      "status_idstr": "3776204349960510",
      "ptype": 0,
      "allow_all_comment": true,
      "avatar_large": "https://tva4.sinaimg.cn/crop.0.20.160.160.180/e8757091jw1eak59nkesqj204g05kmxf.jpg?KID=imgbed,tva&Expires=1698852417&ssig=fJCcj0Nb1k",
      "avatar_hd": "https://tva4.sinaimg.cn/crop.0.20.160.160.1024/e8757091jw1eak59nkesqj204g05kmxf.jpg?KID=imgbed,tva&Expires=1698852417&ssig=gJ4ap2QyeP",
      "verified_reason": "",
      "verified_trade": "",
      "verified_reason_url": "",
      "verified_source": "",
      "verified_source_url": "",
      "follow_me": false,
      "like": false,
      "like_me": false,
      "online_status": 0,
      "bi_followers_count": 258,
      "lang": "zh-cn",
      "star": 0,
      "mbtype": 0,
      "mbrank": 0,
      "svip": 0,
      "vvip": 0,
      "mb_expire_time": 0,
      "block_word": 0,
      "block_app": 0,
      "chaohua_ability": 0,
      "brand_ability": 0,
      "nft_ability": 0,
      "vplus_ability": 0,
      "wenda_ability": 0,
      "live_ability": 0,
      "gongyi_ability": 0,
      "paycolumn_ability": 0,
      "newbrand_ability": 0,
      "ecommerce_ability": 0,
      "hardfan_ability": 0,
      "wbcolumn_ability": 0,
      "interaction_user": 0,
      "audio_ability": 0,
      "credit_score": 80,
      "user_ability": 0,
      "urank": 8,
      "story_read_state": -1,
      "vclub_member": 0,
      "is_teenager": 0,
      "is_guardian": 0,
      "is_teenager_list": 0,
      "pc_new": 0,
      "special_follow": false,
      "planet_video": 0,
      "video_mark": 0,
      "live_status": 0,
      "user_ability_extend": 0,
      "status_total_counter": {
        "total_cnt": 15271,
        "repost_cnt": 15235,
        "comment_cnt": 5,
        "like_cnt": 31,
        "comment_like_cnt": 0
      },
      "video_total_counter": {
        "play_cnt": -1
      },
      "brand_account": 0,
      "hongbaofei": 0,
      "green_mode": 0,
      "urisk": 4398047035392,
      "unfollowing_recom_switch": 1,
      "block": 0,
      "block_me": 0,
      "avatar_type": 0,
      "is_big": 0,
      "auth_status": 0,
      "auth_realname": null,
      "auth_career": null,
      "auth_career_name": null,
      "show_auth": 0,
      "fansIcon": {
        "fans_uid": 3900010641,
        "val": 0,
        "member_rank": 0,
        "svip": 0,
        "vvip": 0,
        "lighting": false,
        "icon_url": "",
        "uid": 3900010641,
        "name": ""
      }
    },
    {
      "id": 5124093760,
      "idstr": "5124093760",
      "class": 1,
      "screen_name": "琳梓汐_354",
      "name": "琳梓汐_354",
      "province": "11",
      "city": "1000",
      "location": "北京",
      "description": "",
      "url": "",
      "profile_image_url": "https://tva2.sinaimg.cn/crop.0.0.480.480.50/005AMaRyjw8eizhbdbqhpj30dc0dcmxk.jpg?KID=imgbed,tva&Expires=1698852417&ssig=xSZalb%2Bljo",
      "light_ring": false,
      "profile_url": "u/5124093760",
      "domain": "",
      "weihao": "",
      "gender": "f",
      "followers_count": 0,
      "followers_count_str": "0",
      "friends_count": 98,
      "pagefriends_count": 1,
      "statuses_count": 0,
      "video_status_count": 0,
      "video_play_count": 0,
      "super_topic_not_syn_count": 0,
      "favourites_count": 0,
      "created_at": "Sat Apr 26 19:17:30 +0800 2014",
      "following": false,
      "allow_all_act_msg": false,
      "geo_enabled": true,
      "verified": false,
      "verified_type": -1,
      "remark": "",
      "insecurity": {
        "sexual_content": false
      },
      "status_id": -1,
      "status_idstr": "-1",
      "ptype": 0,
      "allow_all_comment": true,
      "avatar_large": "https://tva2.sinaimg.cn/crop.0.0.480.480.180/005AMaRyjw8eizhbdbqhpj30dc0dcmxk.jpg?KID=imgbed,tva&Expires=1698852417&ssig=2MyZ8w32bY",
      "avatar_hd": "https://tva2.sinaimg.cn/crop.0.0.480.480.1024/005AMaRyjw8eizhbdbqhpj30dc0dcmxk.jpg?KID=imgbed,tva&Expires=1698852417&ssig=efJfAv6rUM",
      "verified_reason": "",
      "verified_trade": "",
      "verified_reason_url": "",
      "verified_source": "",
      "verified_source_url": "",
      "follow_me": false,
      "like": false,
      "like_me": false,
      "online_status": 0,
      "bi_followers_count": 0,
      "lang": "zh-cn",
      "star": 0,
      "mbtype": 0,
      "mbrank": 0,
      "svip": 0,
      "vvip": 0,
      "mb_expire_time": 0,
      "block_word": 0,
      "block_app": 0,
      "chaohua_ability": 0,
      "brand_ability": 0,
      "nft_ability": 0,
      "vplus_ability": 0,
      "wenda_ability": 0,
      "live_ability": 0,
      "gongyi_ability": 0,
      "paycolumn_ability": 0,
      "newbrand_ability": 0,
      "ecommerce_ability": 0,
      "hardfan_ability": 0,
      "wbcolumn_ability": 0,
      "interaction_user": 0,
      "audio_ability": 0,
      "credit_score": 80,
      "user_ability": 0,
      "urank": 2,
      "story_read_state": -1,
      "vclub_member": 0,
      "is_teenager": 0,
      "is_guardian": 0,
      "is_teenager_list": 0,
      "pc_new": 0,
      "special_follow": false,
      "planet_video": 0,
      "video_mark": 0,
      "live_status": 0,
      "user_ability_extend": 0,
      "status_total_counter": {
        "total_cnt": 0,
        "repost_cnt": 0,
        "comment_cnt": 0,
        "like_cnt": 0,
        "comment_like_cnt": 0
      },
      "video_total_counter": {
        "play_cnt": -1
      },
      "brand_account": 0,
      "hongbaofei": 0,
      "green_mode": 0,
      "urisk": 0,
      "unfollowing_recom_switch": 1,
      "block": 0,
      "block_me": 0,
      "avatar_type": 0,
      "is_big": 0,
      "auth_status": 0,
      "auth_realname": null,
      "auth_career": null,
      "auth_career_name": null,
      "show_auth": 0,
      "fansIcon": {
        "fans_uid": 5124093760,
        "val": 0,
        "member_rank": 0,
        "svip": 0,
        "vvip": 0,
        "lighting": false,
        "icon_url": "",
        "uid": 5124093760,
        "name": ""
      }
    },
    {
      "id": 3953678289,
      "idstr": "3953678289",
      "class": 1,
      "screen_name": "冬天982_908",
      "name": "冬天982_908",
      "province": "100",
      "city": "1000",
      "location": "其他",
      "description": "",
      "url": "",
      "profile_image_url": "https://tva3.sinaimg.cn/crop.0.0.180.180.50/eba857d1jw8ebuue553h8j20500500so.jpg?KID=imgbed,tva&Expires=1698852417&ssig=bxR9ire5Mc",
      "light_ring": false,
      "profile_url": "u/3953678289",
      "domain": "",
      "weihao": "",
      "gender": "m",
      "followers_count": 1,
      "followers_count_str": "1",
      "friends_count": 27,
      "pagefriends_count": 0,
      "statuses_count": 0,
      "video_status_count": 0,
      "video_play_count": 0,
      "super_topic_not_syn_count": 0,
      "favourites_count": 0,
      "created_at": "Tue Dec 24 15:49:44 +0800 2013",
      "following": false,
      "allow_all_act_msg": false,
      "geo_enabled": true,
      "verified": false,
      "verified_type": -1,
      "remark": "",
      "insecurity": {
        "sexual_content": false
      },
      "status_id": -1,
      "status_idstr": "-1",
      "ptype": 0,
      "allow_all_comment": true,
      "avatar_large": "https://tva3.sinaimg.cn/crop.0.0.180.180.180/eba857d1jw8ebuue553h8j20500500so.jpg?KID=imgbed,tva&Expires=1698852417&ssig=rhjq3nXEo1",
      "avatar_hd": "https://tva3.sinaimg.cn/crop.0.0.180.180.1024/eba857d1jw8ebuue553h8j20500500so.jpg?KID=imgbed,tva&Expires=1698852417&ssig=8BqaqX1%2B0I",
      "verified_reason": "",
      "verified_trade": "",
      "verified_reason_url": "",
      "verified_source": "",
      "verified_source_url": "",
      "follow_me": false,
      "like": false,
      "like_me": false,
      "online_status": 0,
      "bi_followers_count": 1,
      "lang": "zh-cn",
      "star": 0,
      "mbtype": 0,
      "mbrank": 0,
      "svip": 0,
      "vvip": 0,
      "mb_expire_time": 0,
      "block_word": 0,
      "block_app": 0,
      "chaohua_ability": 0,
      "brand_ability": 0,
      "nft_ability": 0,
      "vplus_ability": 0,
      "wenda_ability": 0,
      "live_ability": 0,
      "gongyi_ability": 0,
      "paycolumn_ability": 0,
      "newbrand_ability": 0,
      "ecommerce_ability": 0,
      "hardfan_ability": 0,
      "wbcolumn_ability": 0,
      "interaction_user": 0,
      "audio_ability": 0,
      "credit_score": 80,
      "user_ability": 0,
      "urank": 0,
      "story_read_state": -1,
      "vclub_member": 0,
      "is_teenager": 0,
      "is_guardian": 0,
      "is_teenager_list": 0,
      "pc_new": 0,
      "special_follow": false,
      "planet_video": 0,
      "video_mark": 0,
      "live_status": 0,
      "user_ability_extend": 0,
      "status_total_counter": {
        "total_cnt": 0,
        "repost_cnt": 0,
        "comment_cnt": 0,
        "like_cnt": 0,
        "comment_like_cnt": 0
      },
      "video_total_counter": {
        "play_cnt": -1
      },
      "brand_account": 0,
      "hongbaofei": 0,
      "green_mode": 0,
      "urisk": 0,
      "unfollowing_recom_switch": 1,
      "block": 0,
      "block_me": 0,
      "avatar_type": 0,
      "is_big": 0,
      "auth_status": 0,
      "auth_realname": null,
      "auth_career": null,
      "auth_career_name": null,
      "show_auth": 0,
      "fansIcon": {
        "fans_uid": 3953678289,
        "val": 0,
        "member_rank": 0,
        "svip": 0,
        "vvip": 0,
        "lighting": false,
        "icon_url": "",
        "uid": 3953678289,
        "name": ""
      }
    },
    {
      "id": 5142509577,
      "idstr": "5142509577",
      "class": 1,
      "screen_name": "呼啦啦-啦啦啦啦",
      "name": "呼啦啦-啦啦啦啦",
      "province": "400",
      "city": "11",
      "location": "海外 新加坡",
      "description": "",
      "url": "",
      "profile_image_url": "https://tva4.sinaimg.cn/crop.0.0.640.640.50/005C1rERjw8eh3iw5ie16j30hs0hsdgs.jpg?KID=imgbed,tva&Expires=1698852417&ssig=wRlMajhRPh",
      "light_ring": false,
      "profile_url": "u/5142509577",
      "domain": "",
      "weihao": "",
      "gender": "f",
      "followers_count": 17,
      "followers_count_str": "17",
      "friends_count": 86,
      "pagefriends_count": 0,
      "statuses_count": 12,
      "video_status_count": 0,
      "video_play_count": 0,
      "super_topic_not_syn_count": 0,
      "favourites_count": 1,
      "created_at": "Wed May 14 12:21:56 +0800 2014",
      "following": false,
      "allow_all_act_msg": false,
      "geo_enabled": true,
      "verified": false,
      "verified_type": -1,
      "remark": "",
      "insecurity": {
        "sexual_content": false
      },
      "status_id": 3720409868734312,
      "status_idstr": "3720409868734312",
      "ptype": 0,
      "allow_all_comment": true,
      "avatar_large": "https://tva4.sinaimg.cn/crop.0.0.640.640.180/005C1rERjw8eh3iw5ie16j30hs0hsdgs.jpg?KID=imgbed,tva&Expires=1698852417&ssig=0K%2F6dAQWUZ",
      "avatar_hd": "https://tva4.sinaimg.cn/crop.0.0.640.640.1024/005C1rERjw8eh3iw5ie16j30hs0hsdgs.jpg?KID=imgbed,tva&Expires=1698852417&ssig=vaB8nTXpHT",
      "verified_reason": "",
      "verified_trade": "",
      "verified_reason_url": "",
      "verified_source": "",
      "verified_source_url": "",
      "follow_me": false,
      "like": false,
      "like_me": false,
      "online_status": 0,
      "bi_followers_count": 1,
      "lang": "zh-cn",
      "star": 0,
      "mbtype": 0,
      "mbrank": 0,
      "svip": 0,
      "vvip": 0,
      "mb_expire_time": 0,
      "block_word": 0,
      "block_app": 0,
      "chaohua_ability": 0,
      "brand_ability": 0,
      "nft_ability": 0,
      "vplus_ability": 0,
      "wenda_ability": 0,
      "live_ability": 0,
      "gongyi_ability": 0,
      "paycolumn_ability": 0,
      "newbrand_ability": 0,
      "ecommerce_ability": 0,
      "hardfan_ability": 0,
      "wbcolumn_ability": 0,
      "interaction_user": 0,
      "audio_ability": 0,
      "credit_score": 80,
      "user_ability": 0,
      "urank": 5,
      "story_read_state": -1,
      "vclub_member": 0,
      "is_teenager": 0,
      "is_guardian": 0,
      "is_teenager_list": 0,
      "pc_new": 0,
      "special_follow": false,
      "planet_video": 0,
      "video_mark": 0,
      "live_status": 0,
      "user_ability_extend": 0,
      "status_total_counter": {
        "total_cnt": 18,
        "repost_cnt": 0,
        "comment_cnt": 18,
        "like_cnt": 0,
        "comment_like_cnt": 0
      },
      "video_total_counter": {
        "play_cnt": -1
      },
      "brand_account": 0,
      "hongbaofei": 0,
      "green_mode": 0,
      "urisk": 0,
      "unfollowing_recom_switch": 1,
      "block": 0,
      "block_me": 0,
      "avatar_type": 0,
      "is_big": 0,
      "auth_status": 0,
      "auth_realname": null,
      "auth_career": null,
      "auth_career_name": null,
      "show_auth": 0,
      "fansIcon": {
        "fans_uid": 5142509577,
        "val": 0,
        "member_rank": 0,
        "svip": 0,
        "vvip": 0,
        "lighting": false,
        "icon_url": "",
        "uid": 5142509577,
        "name": ""
      }
    },
    {
      "id": 5142033174,
      "idstr": "5142033174",
      "class": 1,
      "screen_name": "Sunshine小孫孫",
      "name": "Sunshine小孫孫",
      "province": "37",
      "city": "1",
      "location": "山东 济南",
      "description": "",
      "url": "",
      "profile_image_url": "https://tva2.sinaimg.cn/crop.0.0.640.640.50/005BZrIWjw8ewkphusqvpj30hs0htjs7.jpg?KID=imgbed,tva&Expires=1698852417&ssig=6llaKBZ0aA",
      "light_ring": false,
      "cover_image_phone": "https://ww3.sinaimg.cn/crop.0.0.640.640.640/a1d3feabjw1eca1ktsx9tj20hs0hsjtk.jpg",
      "profile_url": "u/5142033174",
      "domain": "",
      "weihao": "",
      "gender": "f",
      "followers_count": 31,
      "followers_count_str": "31",
      "friends_count": 68,
      "pagefriends_count": 0,
      "statuses_count": 91,
      "video_status_count": 0,
      "video_play_count": 0,
      "super_topic_not_syn_count": 0,
      "favourites_count": 0,
      "created_at": "Mon May 12 12:27:50 +0800 2014",
      "following": false,
      "allow_all_act_msg": false,
      "geo_enabled": true,
      "verified": false,
      "verified_type": -1,
      "remark": "",
      "insecurity": {
        "sexual_content": false
      },
      "status_id": 4836628880949856,
      "status_idstr": "4836628880949856",
      "ptype": 0,
      "allow_all_comment": true,
      "avatar_large": "https://tva2.sinaimg.cn/crop.0.0.640.640.180/005BZrIWjw8ewkphusqvpj30hs0htjs7.jpg?KID=imgbed,tva&Expires=1698852417&ssig=pONR8TVT7h",
      "avatar_hd": "https://tva2.sinaimg.cn/crop.0.0.640.640.1024/005BZrIWjw8ewkphusqvpj30hs0htjs7.jpg?KID=imgbed,tva&Expires=1698852417&ssig=gaCyd83Rqp",
      "verified_reason": "",
      "verified_trade": "",
      "verified_reason_url": "",
      "verified_source": "",
      "verified_source_url": "",
      "follow_me": false,
      "like": false,
      "like_me": false,
      "online_status": 0,
      "bi_followers_count": 14,
      "lang": "zh-cn",
      "star": 0,
      "mbtype": 0,
      "mbrank": 0,
      "svip": 0,
      "vvip": 0,
      "mb_expire_time": 0,
      "block_word": 0,
      "block_app": 0,
      "chaohua_ability": 0,
      "brand_ability": 0,
      "nft_ability": 0,
      "vplus_ability": 0,
      "wenda_ability": 0,
      "live_ability": 0,
      "gongyi_ability": 0,
      "paycolumn_ability": 0,
      "newbrand_ability": 0,
      "ecommerce_ability": 0,
      "hardfan_ability": 0,
      "wbcolumn_ability": 0,
      "interaction_user": 0,
      "audio_ability": 0,
      "credit_score": 80,
      "user_ability": 0,
      "urank": 11,
      "story_read_state": -1,
      "vclub_member": 0,
      "is_teenager": 0,
      "is_guardian": 0,
      "is_teenager_list": 0,
      "pc_new": 0,
      "special_follow": false,
      "planet_video": 0,
      "video_mark": 0,
      "live_status": 0,
      "user_ability_extend": 0,
      "status_total_counter": {
        "total_cnt": 65,
        "repost_cnt": 3,
        "comment_cnt": 25,
        "like_cnt": 37,
        "comment_like_cnt": 0
      },
      "video_total_counter": {
        "play_cnt": -1
      },
      "brand_account": 0,
      "hongbaofei": 0,
      "green_mode": 0,
      "urisk": 0,
      "unfollowing_recom_switch": 1,
      "block": 0,
      "block_me": 0,
      "avatar_type": 0,
      "is_big": 0,
      "auth_status": 0,
      "auth_realname": null,
      "auth_career": null,
      "auth_career_name": null,
      "show_auth": 0,
      "fansIcon": {
        "fans_uid": 5142033174,
        "val": 0,
        "member_rank": 0,
        "svip": 0,
        "vvip": 0,
        "lighting": false,
        "icon_url": "",
        "uid": 5142033174,
        "name": ""
      }
    },
    {
      "id": 5143560113,
      "idstr": "5143560113",
      "class": 1,
      "screen_name": "幸福兜了一个圈",
      "name": "幸福兜了一个圈",
      "province": "41",
      "city": "1",
      "location": "河南 郑州",
      "description": "",
      "url": "",
      "profile_image_url": "https://tva3.sinaimg.cn/crop.0.0.511.511.50/005C5QWZjw8f1luqmo00vj30e70e8aal.jpg?KID=imgbed,tva&Expires=1698852417&ssig=vxKEZrVtDl",
      "light_ring": false,
      "cover_image_phone": "https://ww3.sinaimg.cn/crop.0.0.640.640.640/6ce2240djw1e9odcin216j20hs0hstd8.jpg",
      "profile_url": "u/5143560113",
      "domain": "",
      "weihao": "",
      "gender": "f",
      "followers_count": 70,
      "followers_count_str": "70",
      "friends_count": 521,
      "pagefriends_count": 3,
      "statuses_count": 1668,
      "video_status_count": 0,
      "video_play_count": 0,
      "super_topic_not_syn_count": 0,
      "favourites_count": 227,
      "created_at": "Mon May 12 00:03:59 +0800 2014",
      "following": false,
      "allow_all_act_msg": false,
      "geo_enabled": true,
      "verified": false,
      "verified_type": -1,
      "remark": "",
      "insecurity": {
        "sexual_content": false
      },
      "status_id": 4957641756640512,
      "status_idstr": "4957641756640512",
      "ptype": 0,
      "allow_all_comment": true,
      "avatar_large": "https://tva3.sinaimg.cn/crop.0.0.511.511.180/005C5QWZjw8f1luqmo00vj30e70e8aal.jpg?KID=imgbed,tva&Expires=1698852417&ssig=vITd4MRSLQ",
      "avatar_hd": "https://tva3.sinaimg.cn/crop.0.0.511.511.1024/005C5QWZjw8f1luqmo00vj30e70e8aal.jpg?KID=imgbed,tva&Expires=1698852417&ssig=sQ67vQfQSC",
      "verified_reason": "",
      "verified_trade": "",
      "verified_reason_url": "",
      "verified_source": "",
      "verified_source_url": "",
      "follow_me": false,
      "like": false,
      "like_me": false,
      "online_status": 0,
      "bi_followers_count": 19,
      "lang": "zh-cn",
      "star": 0,
      "mbtype": 0,
      "mbrank": 0,
      "svip": 0,
      "vvip": 0,
      "mb_expire_time": 0,
      "block_word": 0,
      "block_app": 0,
      "chaohua_ability": 0,
      "brand_ability": 0,
      "nft_ability": 0,
      "vplus_ability": 0,
      "wenda_ability": 0,
      "live_ability": 0,
      "gongyi_ability": 0,
      "paycolumn_ability": 0,
      "newbrand_ability": 0,
      "ecommerce_ability": 0,
      "hardfan_ability": 0,
      "wbcolumn_ability": 0,
      "interaction_user": 0,
      "audio_ability": 0,
      "credit_score": 80,
      "user_ability": 36700160,
      "urank": 14,
      "story_read_state": -1,
      "vclub_member": 0,
      "is_teenager": 0,
      "is_guardian": 0,
      "is_teenager_list": 0,
      "pc_new": 0,
      "special_follow": false,
      "planet_video": 0,
      "video_mark": 0,
      "live_status": 0,
      "user_ability_extend": 0,
      "status_total_counter": {
        "total_cnt": 120,
        "repost_cnt": 2,
        "comment_cnt": 30,
        "like_cnt": 88,
        "comment_like_cnt": 0
      },
      "video_total_counter": {
        "play_cnt": 13
      },
      "brand_account": 0,
      "hongbaofei": 0,
      "green_mode": 0,
      "urisk": 0,
      "unfollowing_recom_switch": 1,
      "block": 0,
      "block_me": 0,
      "avatar_type": 0,
      "is_big": 0,
      "auth_status": 0,
      "auth_realname": null,
      "auth_career": null,
      "auth_career_name": null,
      "show_auth": 0,
      "fansIcon": {
        "fans_uid": 5143560113,
        "val": 0,
        "member_rank": 0,
        "svip": 0,
        "vvip": 0,
        "lighting": false,
        "icon_url": "",
        "uid": 5143560113,
        "name": ""
      }
    },
    {
      "id": 5143778788,
      "idstr": "5143778788",
      "class": 1,
      "screen_name": "zhe-哲噶",
      "name": "zhe-哲噶",
      "province": "11",
      "city": "1",
      "location": "北京 东城区",
      "description": "",
      "url": "",
      "profile_image_url": "https://tva1.sinaimg.cn/crop.0.0.540.540.50/005C6LQ0jw8egbwbk34h9j30f00f0jrn.jpg?KID=imgbed,tva&Expires=1698852417&ssig=f43sQgwBH4",
      "light_ring": false,
      "cover_image_phone": "https://ww1.sinaimg.cn/crop.0.0.640.640.640/549d0121tw1egm1kjly3jj20hs0hsq4f.jpg",
      "profile_url": "u/5143778788",
      "domain": "",
      "weihao": "",
      "gender": "m",
      "followers_count": 28,
      "followers_count_str": "28",
      "friends_count": 224,
      "pagefriends_count": 19,
      "statuses_count": 128,
      "video_status_count": 0,
      "video_play_count": 0,
      "super_topic_not_syn_count": 0,
      "favourites_count": 41,
      "created_at": "Mon May 12 23:09:24 +0800 2014",
      "following": false,
      "allow_all_act_msg": false,
      "geo_enabled": true,
      "verified": false,
      "verified_type": -1,
      "remark": "",
      "insecurity": {
        "sexual_content": false
      },
      "status_id": 4769154576419349,
      "status_idstr": "4769154576419349",
      "ptype": 0,
      "allow_all_comment": true,
      "avatar_large": "https://tva1.sinaimg.cn/crop.0.0.540.540.180/005C6LQ0jw8egbwbk34h9j30f00f0jrn.jpg?KID=imgbed,tva&Expires=1698852417&ssig=5Mhtywkj1J",
      "avatar_hd": "https://tva1.sinaimg.cn/crop.0.0.540.540.1024/005C6LQ0jw8egbwbk34h9j30f00f0jrn.jpg?KID=imgbed,tva&Expires=1698852417&ssig=6FIS4HXwf1",
      "verified_reason": "",
      "verified_trade": "",
      "verified_reason_url": "",
      "verified_source": "",
      "verified_source_url": "",
      "follow_me": false,
      "like": false,
      "like_me": false,
      "online_status": 0,
      "bi_followers_count": 14,
      "lang": "zh-cn",
      "star": 0,
      "mbtype": 0,
      "mbrank": 0,
      "svip": 0,
      "vvip": 0,
      "mb_expire_time": 0,
      "block_word": 0,
      "block_app": 0,
      "chaohua_ability": 0,
      "brand_ability": 0,
      "nft_ability": 0,
      "vplus_ability": 0,
      "wenda_ability": 0,
      "live_ability": 0,
      "gongyi_ability": 0,
      "paycolumn_ability": 0,
      "newbrand_ability": 0,
      "ecommerce_ability": 0,
      "hardfan_ability": 0,
      "wbcolumn_ability": 0,
      "interaction_user": 0,
      "audio_ability": 0,
      "credit_score": 80,
      "user_ability": 2098176,
      "urank": 11,
      "story_read_state": -1,
      "vclub_member": 0,
      "is_teenager": 0,
      "is_guardian": 0,
      "is_teenager_list": 0,
      "pc_new": 0,
      "special_follow": false,
      "planet_video": 0,
      "video_mark": 0,
      "live_status": 0,
      "user_ability_extend": 0,
      "status_total_counter": {
        "total_cnt": 14,
        "repost_cnt": 2,
        "comment_cnt": 7,
        "like_cnt": 5,
        "comment_like_cnt": 0
      },
      "video_total_counter": {
        "play_cnt": -1
      },
      "brand_account": 0,
      "hongbaofei": 0,
      "green_mode": 0,
      "urisk": 0,
      "unfollowing_recom_switch": 1,
      "block": 0,
      "block_me": 0,
      "avatar_type": 0,
      "is_big": 0,
      "auth_status": 0,
      "auth_realname": null,
      "auth_career": null,
      "auth_career_name": null,
      "show_auth": 0,
      "fansIcon": {
        "fans_uid": 5143778788,
        "val": 0,
        "member_rank": 0,
        "svip": 0,
        "vvip": 0,
        "lighting": false,
        "icon_url": "",
        "uid": 5143778788,
        "name": ""
      }
    },
    {
      "id": 5135912150,
      "idstr": "5135912150",
      "class": 1,
      "screen_name": "Angela瑶酱",
      "name": "Angela瑶酱",
      "province": "43",
      "city": "1000",
      "location": "湖南",
      "description": "四叶草永追随，，大爱Tfboys",
      "url": "",
      "profile_image_url": "https://tva1.sinaimg.cn/crop.0.0.720.720.50/005BzLmKjw8ege9j6myhoj30k00k00te.jpg?KID=imgbed,tva&Expires=1698852417&ssig=dyftC5iFaf",
      "light_ring": false,
      "profile_url": "u/5135912150",
      "domain": "",
      "weihao": "",
      "gender": "f",
      "followers_count": 6,
      "followers_count_str": "6",
      "friends_count": 71,
      "pagefriends_count": 2,
      "statuses_count": 41,
      "video_status_count": 0,
      "video_play_count": 0,
      "super_topic_not_syn_count": 0,
      "favourites_count": 0,
      "created_at": "Fri May 09 13:16:56 +0800 2014",
      "following": false,
      "allow_all_act_msg": false,
      "geo_enabled": true,
      "verified": false,
      "verified_type": -1,
      "remark": "",
      "insecurity": {
        "sexual_content": false
      },
      "status_id": 4874024477788456,
      "status_idstr": "4874024477788456",
      "ptype": 0,
      "allow_all_comment": true,
      "avatar_large": "https://tva1.sinaimg.cn/crop.0.0.720.720.180/005BzLmKjw8ege9j6myhoj30k00k00te.jpg?KID=imgbed,tva&Expires=1698852417&ssig=4wAO6wwAyW",
      "avatar_hd": "https://tva1.sinaimg.cn/crop.0.0.720.720.1024/005BzLmKjw8ege9j6myhoj30k00k00te.jpg?KID=imgbed,tva&Expires=1698852417&ssig=HNqA6%2F89fz",
      "verified_reason": "",
      "verified_trade": "",
      "verified_reason_url": "",
      "verified_source": "",
      "verified_source_url": "",
      "follow_me": false,
      "like": false,
      "like_me": false,
      "online_status": 0,
      "bi_followers_count": 3,
      "lang": "zh-cn",
      "star": 0,
      "mbtype": 0,
      "mbrank": 0,
      "svip": 0,
      "vvip": 0,
      "mb_expire_time": 0,
      "block_word": 0,
      "block_app": 0,
      "chaohua_ability": 0,
      "brand_ability": 0,
      "nft_ability": 0,
      "vplus_ability": 0,
      "wenda_ability": 0,
      "live_ability": 0,
      "gongyi_ability": 0,
      "paycolumn_ability": 0,
      "newbrand_ability": 0,
      "ecommerce_ability": 0,
      "hardfan_ability": 0,
      "wbcolumn_ability": 0,
      "interaction_user": 0,
      "audio_ability": 0,
      "credit_score": 80,
      "user_ability": 0,
      "urank": 4,
      "story_read_state": -1,
      "vclub_member": 0,
      "is_teenager": 0,
      "is_guardian": 0,
      "is_teenager_list": 0,
      "pc_new": 0,
      "special_follow": false,
      "planet_video": 0,
      "video_mark": 0,
      "live_status": 0,
      "user_ability_extend": 0,
      "status_total_counter": {
        "total_cnt": 17,
        "repost_cnt": 1,
        "comment_cnt": 9,
        "like_cnt": 7,
        "comment_like_cnt": 0
      },
      "video_total_counter": {
        "play_cnt": -1
      },
      "brand_account": 0,
      "hongbaofei": 0,
      "green_mode": 0,
      "urisk": 0,
      "unfollowing_recom_switch": 1,
      "block": 0,
      "block_me": 0,
      "avatar_type": 0,
      "is_big": 0,
      "auth_status": 0,
      "auth_realname": null,
      "auth_career": null,
      "auth_career_name": null,
      "show_auth": 0,
      "fansIcon": {
        "fans_uid": 5135912150,
        "val": 0,
        "member_rank": 0,
        "svip": 0,
        "vvip": 0,
        "lighting": false,
        "icon_url": "",
        "uid": 5135912150,
        "name": ""
      }
    },
    {
      "id": 3933515903,
      "idstr": "3933515903",
      "class": 1,
      "screen_name": "普罗米修斯杰林",
      "name": "普罗米修斯杰林",
      "province": "43",
      "city": "31",
      "location": "湖南 湘西土家族苗族自治州",
      "description": "杰林 请你知道没有梦想的工作只会慢慢的榨干你的激情和生命！",
      "url": "",
      "profile_image_url": "https://tva3.sinaimg.cn/crop.0.0.720.720.50/ea74b07fjw8egvlxbo0ufj20k00k0aat.jpg?KID=imgbed,tva&Expires=1698852417&ssig=uM8VybzCEX",
      "light_ring": false,
      "cover_image_phone": "https://ww1.sinaimg.cn/crop.0.0.640.640.640/549d0121tw1egm1kjly3jj20hs0hsq4f.jpg",
      "profile_url": "u/3933515903",
      "domain": "",
      "weihao": "",
      "gender": "m",
      "followers_count": 231,
      "followers_count_str": "231",
      "friends_count": 390,
      "pagefriends_count": 5,
      "statuses_count": 174,
      "video_status_count": 10,
      "video_play_count": 0,
      "super_topic_not_syn_count": 0,
      "favourites_count": 5,
      "created_at": "Fri Dec 13 15:22:21 +0800 2013",
      "following": false,
      "allow_all_act_msg": false,
      "geo_enabled": true,
      "verified": false,
      "verified_type": -1,
      "remark": "",
      "insecurity": {
        "sexual_content": false
      },
      "status_id": 4944959579095482,
      "status_idstr": "4944959579095482",
      "ptype": 0,
      "allow_all_comment": true,
      "avatar_large": "https://tva3.sinaimg.cn/crop.0.0.720.720.180/ea74b07fjw8egvlxbo0ufj20k00k0aat.jpg?KID=imgbed,tva&Expires=1698852417&ssig=u4h6QGfAI0",
      "avatar_hd": "https://tva3.sinaimg.cn/crop.0.0.720.720.1024/ea74b07fjw8egvlxbo0ufj20k00k0aat.jpg?KID=imgbed,tva&Expires=1698852417&ssig=dsz1brM9Mu",
      "verified_reason": "",
      "verified_trade": "",
      "verified_reason_url": "",
      "verified_source": "",
      "verified_source_url": "",
      "follow_me": false,
      "like": false,
      "like_me": false,
      "online_status": 0,
      "bi_followers_count": 34,
      "lang": "zh-cn",
      "star": 0,
      "mbtype": 0,
      "mbrank": 0,
      "svip": 0,
      "vvip": 0,
      "mb_expire_time": 0,
      "block_word": 0,
      "block_app": 0,
      "chaohua_ability": 0,
      "brand_ability": 0,
      "nft_ability": 0,
      "vplus_ability": 0,
      "wenda_ability": 0,
      "live_ability": 0,
      "gongyi_ability": 0,
      "paycolumn_ability": 0,
      "newbrand_ability": 0,
      "ecommerce_ability": 0,
      "hardfan_ability": 0,
      "wbcolumn_ability": 0,
      "interaction_user": 0,
      "audio_ability": 0,
      "credit_score": 80,
      "user_ability": 3407872,
      "urank": 14,
      "story_read_state": -1,
      "vclub_member": 0,
      "is_teenager": 0,
      "is_guardian": 0,
      "is_teenager_list": 0,
      "pc_new": 0,
      "special_follow": false,
      "planet_video": 0,
      "video_mark": 2,
      "live_status": 0,
      "user_ability_extend": 0,
      "status_total_counter": {
        "total_cnt": 117,
        "repost_cnt": 5,
        "comment_cnt": 24,
        "like_cnt": 88,
        "comment_like_cnt": 0
      },
      "video_total_counter": {
        "play_cnt": 97
      },
      "brand_account": 0,
      "hongbaofei": 0,
      "green_mode": 0,
      "urisk": 0,
      "unfollowing_recom_switch": 1,
      "block": 0,
      "block_me": 0,
      "avatar_type": 0,
      "is_big": 0,
      "auth_status": 0,
      "auth_realname": null,
      "auth_career": null,
      "auth_career_name": null,
      "show_auth": 0,
      "fansIcon": {
        "fans_uid": 3933515903,
        "val": 0,
        "member_rank": 0,
        "svip": 0,
        "vvip": 0,
        "lighting": false,
        "icon_url": "",
        "uid": 3933515903,
        "name": ""
      }
    },
    {
      "id": 5016771552,
      "idstr": "5016771552",
      "class": 1,
      "screen_name": "美丽枫叶2014",
      "name": "美丽枫叶2014",
      "province": "41",
      "city": "1",
      "location": "河南 郑州",
      "description": "不在困难面前屈服，不在挫折面前低头，不在失败面前却步，勇敢前进！",
      "url": "",
      "profile_image_url": "https://tva1.sinaimg.cn/crop.0.0.1080.1080.50/005tvRscjw8es2ynfhze4j30u00u0774.jpg?KID=imgbed,tva&Expires=1698852417&ssig=EGK1ZgzJEQ",
      "light_ring": false,
      "cover_image_phone": "https://ww2.sinaimg.cn/crop.0.0.640.640.640/a1d3feabjw1ecat8op0e1j20hs0hswgu.jpg",
      "profile_url": "u/5016771552",
      "domain": "",
      "weihao": "",
      "gender": "m",
      "followers_count": 59,
      "followers_count_str": "59",
      "friends_count": 240,
      "pagefriends_count": 2,
      "statuses_count": 31,
      "video_status_count": 0,
      "video_play_count": 0,
      "super_topic_not_syn_count": 0,
      "favourites_count": 2,
      "created_at": "Wed Jan 29 23:56:37 +0800 2014",
      "following": false,
      "allow_all_act_msg": false,
      "geo_enabled": true,
      "verified": false,
      "verified_type": -1,
      "remark": "",
      "insecurity": {
        "sexual_content": false
      },
      "status_id": 4956192952287345,
      "status_idstr": "4956192952287345",
      "ptype": 0,
      "allow_all_comment": true,
      "avatar_large": "https://tva1.sinaimg.cn/crop.0.0.1080.1080.180/005tvRscjw8es2ynfhze4j30u00u0774.jpg?KID=imgbed,tva&Expires=1698852417&ssig=yW4ra6oKQs",
      "avatar_hd": "https://tva1.sinaimg.cn/crop.0.0.1080.1080.1024/005tvRscjw8es2ynfhze4j30u00u0774.jpg?KID=imgbed,tva&Expires=1698852417&ssig=P7yfN28u41",
      "verified_reason": "",
      "verified_trade": "",
      "verified_reason_url": "",
      "verified_source": "",
      "verified_source_url": "",
      "follow_me": false,
      "like": false,
      "like_me": false,
      "online_status": 0,
      "bi_followers_count": 7,
      "lang": "zh-cn",
      "star": 0,
      "mbtype": 0,
      "mbrank": 0,
      "svip": 0,
      "vvip": 0,
      "mb_expire_time": 0,
      "block_word": 0,
      "block_app": 0,
      "chaohua_ability": 0,
      "brand_ability": 0,
      "nft_ability": 0,
      "vplus_ability": 0,
      "wenda_ability": 0,
      "live_ability": 0,
      "gongyi_ability": 0,
      "paycolumn_ability": 0,
      "newbrand_ability": 0,
      "ecommerce_ability": 0,
      "hardfan_ability": 0,
      "wbcolumn_ability": 0,
      "interaction_user": 0,
      "audio_ability": 0,
      "credit_score": 80,
      "user_ability": 33554432,
      "urank": 9,
      "story_read_state": -1,
      "vclub_member": 0,
      "is_teenager": 0,
      "is_guardian": 0,
      "is_teenager_list": 0,
      "pc_new": 0,
      "special_follow": false,
      "planet_video": 0,
      "video_mark": 0,
      "live_status": 0,
      "user_ability_extend": 0,
      "status_total_counter": {
        "total_cnt": 30,
        "repost_cnt": 2,
        "comment_cnt": 20,
        "like_cnt": 8,
        "comment_like_cnt": 0
      },
      "video_total_counter": {
        "play_cnt": -1
      },
      "brand_account": 0,
      "hongbaofei": 0,
      "green_mode": 0,
      "urisk": 0,
      "unfollowing_recom_switch": 1,
      "block": 0,
      "block_me": 0,
      "avatar_type": 0,
      "is_big": 0,
      "auth_status": 0,
      "auth_realname": null,
      "auth_career": null,
      "auth_career_name": null,
      "show_auth": 0,
      "fansIcon": {
        "fans_uid": 5016771552,
        "val": 0,
        "member_rank": 0,
        "svip": 0,
        "vvip": 0,
        "lighting": false,
        "icon_url": "",
        "uid": 5016771552,
        "name": ""
      }
    },
    {
      "id": 3384767710,
      "idstr": "3384767710",
      "class": 1,
      "screen_name": "-小---寒-",
      "name": "-小---寒-",
      "province": "100",
      "city": "1000",
      "location": "其他",
      "description": "",
      "url": "",
      "profile_image_url": "https://tva2.sinaimg.cn/crop.0.0.180.180.50/c9bf74dejw1e8qgp5bmzyj2050050aa8.jpg?KID=imgbed,tva&Expires=1698852417&ssig=TjIglKcTyv",
      "light_ring": false,
      "profile_url": "u/3384767710",
      "domain": "",
      "weihao": "",
      "gender": "f",
      "followers_count": 315,
      "followers_count_str": "315",
      "friends_count": 779,
      "pagefriends_count": 0,
      "statuses_count": 970,
      "video_status_count": 0,
      "video_play_count": 0,
      "super_topic_not_syn_count": 0,
      "favourites_count": 0,
      "created_at": "Tue May 21 12:49:20 +0800 2013",
      "following": false,
      "allow_all_act_msg": false,
      "geo_enabled": true,
      "verified": false,
      "verified_type": -1,
      "remark": "",
      "insecurity": {
        "sexual_content": false
      },
      "status_id": 3732403229041650,
      "status_idstr": "3732403229041650",
      "ptype": 0,
      "allow_all_comment": true,
      "avatar_large": "https://tva2.sinaimg.cn/crop.0.0.180.180.180/c9bf74dejw1e8qgp5bmzyj2050050aa8.jpg?KID=imgbed,tva&Expires=1698852417&ssig=6el%2BTntQCG",
      "avatar_hd": "https://tva2.sinaimg.cn/crop.0.0.180.180.1024/c9bf74dejw1e8qgp5bmzyj2050050aa8.jpg?KID=imgbed,tva&Expires=1698852417&ssig=2IMglpDUbG",
      "verified_reason": "",
      "verified_trade": "",
      "verified_reason_url": "",
      "verified_source": "",
      "verified_source_url": "",
      "follow_me": false,
      "like": false,
      "like_me": false,
      "online_status": 0,
      "bi_followers_count": 219,
      "lang": "zh-cn",
      "star": 0,
      "mbtype": 0,
      "mbrank": 0,
      "svip": 0,
      "vvip": 0,
      "mb_expire_time": 0,
      "block_word": 0,
      "block_app": 0,
      "chaohua_ability": 0,
      "brand_ability": 0,
      "nft_ability": 0,
      "vplus_ability": 0,
      "wenda_ability": 0,
      "live_ability": 0,
      "gongyi_ability": 0,
      "paycolumn_ability": 0,
      "newbrand_ability": 0,
      "ecommerce_ability": 0,
      "hardfan_ability": 0,
      "wbcolumn_ability": 0,
      "interaction_user": 0,
      "audio_ability": 0,
      "credit_score": 80,
      "user_ability": 0,
      "urank": 7,
      "story_read_state": -1,
      "vclub_member": 0,
      "is_teenager": 0,
      "is_guardian": 0,
      "is_teenager_list": 0,
      "pc_new": 0,
      "special_follow": false,
      "planet_video": 0,
      "video_mark": 0,
      "live_status": 0,
      "user_ability_extend": 0,
      "status_total_counter": {
        "total_cnt": 301,
        "repost_cnt": 71,
        "comment_cnt": 21,
        "like_cnt": 209,
        "comment_like_cnt": 0
      },
      "video_total_counter": {
        "play_cnt": -1
      },
      "brand_account": 0,
      "hongbaofei": 0,
      "green_mode": 0,
      "urisk": 0,
      "unfollowing_recom_switch": 1,
      "block": 0,
      "block_me": 0,
      "avatar_type": 0,
      "is_big": 0,
      "auth_status": 0,
      "auth_realname": null,
      "auth_career": null,
      "auth_career_name": null,
      "show_auth": 0,
      "fansIcon": {
        "fans_uid": 3384767710,
        "val": 0,
        "member_rank": 0,
        "svip": 0,
        "vvip": 0,
        "lighting": false,
        "icon_url": "",
        "uid": 3384767710,
        "name": ""
      }
    },
    {
      "id": 2671109275,
      "idstr": "2671109275",
      "class": 1,
      "screen_name": "新手指南",
      "name": "新手指南",
      "province": "11",
      "city": "8",
      "location": "北京 海淀区",
      "description": "教授新手使用微博方法专业户，每天推荐方法介绍、微博热点...有问题请call我，@、私信都可以，欢迎骚扰~",
      "url": "http://www.weibo.com/guide/handbook",
      "profile_image_url": "https://tvax1.sinaimg.cn/crop.0.0.180.180.50/002ULHxFly8h8v4gkd2dnj60500503yd02.jpg?KID=imgbed,tva&Expires=1698852417&ssig=LGIs7b3KEb",
      "light_ring": false,
      "cover_image_phone": "https://ww1.sinaimg.cn/crop.0.0.640.640.640/549d0121tw1egm1kjly3jj20hs0hsq4f.jpg",
      "profile_url": "u/2671109275",
      "domain": "",
      "weihao": "",
      "gender": "m",
      "followers_count": 161525185,
      "followers_count_str": "1.62亿",
      "friends_count": 788,
      "pagefriends_count": 9,
      "statuses_count": 30965,
      "video_status_count": 687,
      "video_play_count": 0,
      "super_topic_not_syn_count": 0,
      "favourites_count": 2628,
      "created_at": "Wed Mar 21 10:31:42 +0800 2012",
      "following": false,
      "allow_all_act_msg": true,
      "geo_enabled": true,
      "verified": true,
      "verified_type": 7,
      "remark": "",
      "insecurity": {
        "sexual_content": false
      },
      "status_id": 4963320683824355,
      "status_idstr": "4963320683824355",
      "ptype": 0,
      "allow_all_comment": true,
      "avatar_large": "https://tvax1.sinaimg.cn/crop.0.0.180.180.180/002ULHxFly8h8v4gkd2dnj60500503yd02.jpg?KID=imgbed,tva&Expires=1698852417&ssig=yx0vUUwLba",
      "avatar_hd": "https://tvax1.sinaimg.cn/crop.0.0.180.180.1024/002ULHxFly8h8v4gkd2dnj60500503yd02.jpg?KID=imgbed,tva&Expires=1698852417&ssig=3nmfYGcnGK",
      "verified_reason": "新浪微博新手指南官方微博",
      "verified_trade": "",
      "verified_reason_url": "",
      "verified_source": "",
      "verified_source_url": "",
      "verified_state": 0,
      "verified_level": 3,
      "verified_type_ext": 0,
      "pay_remind": 0,
      "pay_date": "",
      "has_service_tel": false,
      "verified_reason_modified": "",
      "verified_contact_name": "",
      "verified_contact_email": "",
      "verified_contact_mobile": "",
      "follow_me": false,
      "like": false,
      "like_me": false,
      "online_status": 0,
      "bi_followers_count": 660,
      "lang": "zh-cn",
      "star": 0,
      "mbtype": 12,
      "mbrank": 1,
      "svip": 1,
      "vvip": 1,
      "mb_expire_time": 1703347200,
      "block_word": 1,
      "block_app": 1,
      "chaohua_ability": 0,
      "brand_ability": 0,
      "nft_ability": 0,
      "vplus_ability": 0,
      "wenda_ability": 0,
      "live_ability": 0,
      "gongyi_ability": 0,
      "paycolumn_ability": 0,
      "newbrand_ability": 0,
      "ecommerce_ability": 0,
      "hardfan_ability": 1,
      "wbcolumn_ability": 0,
      "interaction_user": 0,
      "audio_ability": 0,
      "credit_score": 80,
      "user_ability": 2359816,
      "cardid": "star_1725",
      "avatargj_id": "gj_vip_575",
      "urank": 48,
      "story_read_state": -1,
      "vclub_member": 0,
      "is_teenager": 0,
      "is_guardian": 0,
      "is_teenager_list": 0,
      "pc_new": 7,
      "special_follow": false,
      "planet_video": 2,
      "video_mark": 15,
      "live_status": 0,
      "user_ability_extend": 0,
      "status_total_counter": {
        "total_cnt": 31288475,
        "repost_cnt": 7917231,
        "comment_cnt": 3814147,
        "like_cnt": 19199456,
        "comment_like_cnt": 357641
      },
      "video_total_counter": {
        "play_cnt": 116392360
      },
      "brand_account": 0,
      "hongbaofei": 0,
      "green_mode": 0,
      "urisk": 0,
      "unfollowing_recom_switch": 1,
      "block": 0,
      "block_me": 0,
      "avatar_type": 0,
      "is_big": 0,
      "auth_status": 0,
      "auth_realname": null,
      "auth_career": null,
      "auth_career_name": null,
      "show_auth": 0,
      "fansIcon": {
        "fans_uid": 2671109275,
        "val": 0,
        "member_rank": 1,
        "svip": 1,
        "vvip": 1,
        "lighting": false,
        "icon_url": "",
        "uid": 2671109275,
        "name": ""
      }
    },
    {
      "id": 5203774397,
      "idstr": "5203774397",
      "class": 1,
      "screen_name": "孰关注名家传播思想",
      "name": "孰关注名家传播思想",
      "province": "400",
      "city": "7",
      "location": "海外 澳大利亚",
      "description": "",
      "url": "",
      "profile_image_url": "https://tva2.sinaimg.cn/crop.0.0.200.200.50/005Gavr7jw1ej5rq61fq3j305k05kmx2.jpg?KID=imgbed,tva&Expires=1698852417&ssig=hjMxW7kAr0",
      "light_ring": false,
      "profile_url": "u/5203774397",
      "domain": "",
      "weihao": "",
      "gender": "m",
      "followers_count": 118,
      "followers_count_str": "118",
      "friends_count": 1538,
      "pagefriends_count": 0,
      "statuses_count": 3577,
      "video_status_count": 0,
      "video_play_count": 0,
      "super_topic_not_syn_count": 0,
      "favourites_count": 0,
      "created_at": "Fri Jul 04 15:48:31 +0800 2014",
      "following": false,
      "allow_all_act_msg": false,
      "geo_enabled": true,
      "verified": false,
      "verified_type": -1,
      "remark": "",
      "insecurity": {
        "sexual_content": false
      },
      "status_id": 3784705386117595,
      "status_idstr": "3784705386117595",
      "ptype": 0,
      "allow_all_comment": true,
      "avatar_large": "https://tva2.sinaimg.cn/crop.0.0.200.200.180/005Gavr7jw1ej5rq61fq3j305k05kmx2.jpg?KID=imgbed,tva&Expires=1698852417&ssig=T5I5t6a2yE",
      "avatar_hd": "https://tva2.sinaimg.cn/crop.0.0.200.200.1024/005Gavr7jw1ej5rq61fq3j305k05kmx2.jpg?KID=imgbed,tva&Expires=1698852417&ssig=MkgD4%2B2fjW",
      "verified_reason": "",
      "verified_trade": "",
      "verified_reason_url": "",
      "verified_source": "",
      "verified_source_url": "",
      "follow_me": false,
      "like": false,
      "like_me": false,
      "online_status": 0,
      "bi_followers_count": 45,
      "lang": "zh-cn",
      "star": 0,
      "mbtype": 0,
      "mbrank": 0,
      "svip": 0,
      "vvip": 0,
      "mb_expire_time": 0,
      "block_word": 0,
      "block_app": 0,
      "chaohua_ability": 0,
      "brand_ability": 0,
      "nft_ability": 0,
      "vplus_ability": 0,
      "wenda_ability": 0,
      "live_ability": 0,
      "gongyi_ability": 0,
      "paycolumn_ability": 0,
      "newbrand_ability": 0,
      "ecommerce_ability": 0,
      "hardfan_ability": 0,
      "wbcolumn_ability": 0,
      "interaction_user": 0,
      "audio_ability": 0,
      "credit_score": 80,
      "user_ability": 0,
      "urank": 7,
      "story_read_state": -1,
      "vclub_member": 0,
      "is_teenager": 0,
      "is_guardian": 0,
      "is_teenager_list": 0,
      "pc_new": 0,
      "special_follow": false,
      "planet_video": 0,
      "video_mark": 0,
      "live_status": 0,
      "user_ability_extend": 0,
      "status_total_counter": {
        "total_cnt": 13,
        "repost_cnt": 1,
        "comment_cnt": 2,
        "like_cnt": 10,
        "comment_like_cnt": 0
      },
      "video_total_counter": {
        "play_cnt": -1
      },
      "brand_account": 0,
      "hongbaofei": 0,
      "green_mode": 0,
      "urisk": 4398047035392,
      "unfollowing_recom_switch": 1,
      "block": 0,
      "block_me": 0,
      "avatar_type": 0,
      "is_big": 0,
      "auth_status": 0,
      "auth_realname": null,
      "auth_career": null,
      "auth_career_name": null,
      "show_auth": 0,
      "fansIcon": {
        "fans_uid": 5203774397,
        "val": 0,
        "member_rank": 0,
        "svip": 0,
        "vvip": 0,
        "lighting": false,
        "icon_url": "",
        "uid": 5203774397,
        "name": ""
      }
    },
    {
      "id": 5064973507,
      "idstr": "5064973507",
      "class": 1,
      "screen_name": "funkboy6",
      "name": "funkboy6",
      "province": "43",
      "city": "2",
      "location": "湖南 株洲",
      "description": "",
      "url": "",
      "profile_image_url": "https://tva3.sinaimg.cn/crop.0.0.200.200.50/005wM6Z5jw1eehgf0f156j305k05k74a.jpg?KID=imgbed,tva&Expires=1698852417&ssig=NZGTAwZl%2FB",
      "light_ring": false,
      "profile_url": "u/5064973507",
      "domain": "",
      "weihao": "",
      "gender": "f",
      "followers_count": 110,
      "followers_count_str": "110",
      "friends_count": 1857,
      "pagefriends_count": 0,
      "statuses_count": 5,
      "video_status_count": 0,
      "video_play_count": 0,
      "super_topic_not_syn_count": 0,
      "favourites_count": 0,
      "created_at": "Tue Mar 11 00:06:42 +0800 2014",
      "following": false,
      "allow_all_act_msg": false,
      "geo_enabled": true,
      "verified": false,
      "verified_type": -1,
      "remark": "",
      "insecurity": {
        "sexual_content": false
      },
      "status_id": 3738515605005838,
      "status_idstr": "3738515605005838",
      "ptype": 0,
      "allow_all_comment": true,
      "avatar_large": "https://tva3.sinaimg.cn/crop.0.0.200.200.180/005wM6Z5jw1eehgf0f156j305k05k74a.jpg?KID=imgbed,tva&Expires=1698852417&ssig=R9bHMO1VQv",
      "avatar_hd": "https://tva3.sinaimg.cn/crop.0.0.200.200.1024/005wM6Z5jw1eehgf0f156j305k05k74a.jpg?KID=imgbed,tva&Expires=1698852417&ssig=yBQz7CxF7J",
      "verified_reason": "",
      "verified_trade": "",
      "verified_reason_url": "",
      "verified_source": "",
      "verified_source_url": "",
      "follow_me": false,
      "like": false,
      "like_me": false,
      "online_status": 0,
      "bi_followers_count": 39,
      "lang": "zh-cn",
      "star": 0,
      "mbtype": 0,
      "mbrank": 0,
      "svip": 0,
      "vvip": 0,
      "mb_expire_time": 0,
      "block_word": 0,
      "block_app": 0,
      "chaohua_ability": 0,
      "brand_ability": 0,
      "nft_ability": 0,
      "vplus_ability": 0,
      "wenda_ability": 0,
      "live_ability": 0,
      "gongyi_ability": 0,
      "paycolumn_ability": 0,
      "newbrand_ability": 0,
      "ecommerce_ability": 0,
      "hardfan_ability": 0,
      "wbcolumn_ability": 0,
      "interaction_user": 0,
      "audio_ability": 0,
      "credit_score": 80,
      "user_ability": 0,
      "urank": 5,
      "story_read_state": -1,
      "vclub_member": 0,
      "is_teenager": 0,
      "is_guardian": 0,
      "is_teenager_list": 0,
      "pc_new": 0,
      "special_follow": false,
      "planet_video": 0,
      "video_mark": 0,
      "live_status": 0,
      "user_ability_extend": 0,
      "status_total_counter": {
        "total_cnt": 4,
        "repost_cnt": 0,
        "comment_cnt": 0,
        "like_cnt": 4,
        "comment_like_cnt": 0
      },
      "video_total_counter": {
        "play_cnt": -1
      },
      "brand_account": 0,
      "hongbaofei": 0,
      "green_mode": 0,
      "urisk": 0,
      "unfollowing_recom_switch": 1,
      "block": 0,
      "block_me": 0,
      "avatar_type": 0,
      "is_big": 0,
      "auth_status": 0,
      "auth_realname": null,
      "auth_career": null,
      "auth_career_name": null,
      "show_auth": 0,
      "fansIcon": {
        "fans_uid": 5064973507,
        "val": 0,
        "member_rank": 0,
        "svip": 0,
        "vvip": 0,
        "lighting": false,
        "icon_url": "",
        "uid": 5064973507,
        "name": ""
      }
    },
    {
      "id": 3278888231,
      "idstr": "3278888231",
      "class": 1,
      "screen_name": "颢艾的忐忑漫步",
      "name": "颢艾的忐忑漫步",
      "province": "11",
      "city": "1000",
      "location": "北京",
      "description": "",
      "url": "",
      "profile_image_url": "https://tva3.sinaimg.cn/crop.0.0.150.150.50/c36fdd27jw1eghp9r0hdfj2046046t8n.jpg?KID=imgbed,tva&Expires=1698852417&ssig=2eoGpuwJM9",
      "light_ring": false,
      "profile_url": "u/3278888231",
      "domain": "",
      "weihao": "",
      "gender": "f",
      "followers_count": 101,
      "followers_count_str": "101",
      "friends_count": 1340,
      "pagefriends_count": 0,
      "statuses_count": 314,
      "video_status_count": 0,
      "video_play_count": 0,
      "super_topic_not_syn_count": 0,
      "favourites_count": 0,
      "created_at": "Thu Mar 28 14:44:59 +0800 2013",
      "following": false,
      "allow_all_act_msg": false,
      "geo_enabled": true,
      "verified": false,
      "verified_type": -1,
      "remark": "",
      "insecurity": {
        "sexual_content": false
      },
      "status_id": 3715673643782425,
      "status_idstr": "3715673643782425",
      "ptype": 0,
      "allow_all_comment": true,
      "avatar_large": "https://tva3.sinaimg.cn/crop.0.0.150.150.180/c36fdd27jw1eghp9r0hdfj2046046t8n.jpg?KID=imgbed,tva&Expires=1698852417&ssig=gh%2Bgkecu%2FJ",
      "avatar_hd": "https://tva3.sinaimg.cn/crop.0.0.150.150.1024/c36fdd27jw1eghp9r0hdfj2046046t8n.jpg?KID=imgbed,tva&Expires=1698852417&ssig=R90QSiSJ8B",
      "verified_reason": "",
      "verified_trade": "",
      "verified_reason_url": "",
      "verified_source": "",
      "verified_source_url": "",
      "follow_me": false,
      "like": false,
      "like_me": false,
      "online_status": 0,
      "bi_followers_count": 65,
      "lang": "zh-cn",
      "star": 0,
      "mbtype": 0,
      "mbrank": 0,
      "svip": 0,
      "vvip": 0,
      "mb_expire_time": 0,
      "block_word": 0,
      "block_app": 0,
      "chaohua_ability": 0,
      "brand_ability": 0,
      "nft_ability": 0,
      "vplus_ability": 0,
      "wenda_ability": 0,
      "live_ability": 0,
      "gongyi_ability": 0,
      "paycolumn_ability": 0,
      "newbrand_ability": 0,
      "ecommerce_ability": 0,
      "hardfan_ability": 0,
      "wbcolumn_ability": 0,
      "interaction_user": 0,
      "audio_ability": 0,
      "credit_score": 80,
      "user_ability": 0,
      "urank": 3,
      "story_read_state": -1,
      "vclub_member": 0,
      "is_teenager": 0,
      "is_guardian": 0,
      "is_teenager_list": 0,
      "pc_new": 0,
      "special_follow": false,
      "planet_video": 0,
      "video_mark": 0,
      "live_status": 0,
      "user_ability_extend": 0,
      "status_total_counter": {
        "total_cnt": 4,
        "repost_cnt": 0,
        "comment_cnt": 0,
        "like_cnt": 4,
        "comment_like_cnt": 0
      },
      "video_total_counter": {
        "play_cnt": -1
      },
      "brand_account": 0,
      "hongbaofei": 0,
      "green_mode": 0,
      "urisk": 4398047035392,
      "unfollowing_recom_switch": 1,
      "block": 0,
      "block_me": 0,
      "avatar_type": 0,
      "is_big": 0,
      "auth_status": 0,
      "auth_realname": null,
      "auth_career": null,
      "auth_career_name": null,
      "show_auth": 0,
      "fansIcon": {
        "fans_uid": 3278888231,
        "val": 0,
        "member_rank": 0,
        "svip": 0,
        "vvip": 0,
        "lighting": false,
        "icon_url": "",
        "uid": 3278888231,
        "name": ""
      }
    }
  ],
  "has_filtered_attentions": false,
  "next_cursor": 0,
  "previous_cursor": 0,
  "total_number": 31,
  "use_sink_stragety": true,
  "has_filtered_fans": true,
  "use_status_strategy": false,
  "show_related_topic": false,
  "display_total_number": 30,
  "display_total_number_str": "30",
  "show_unread": false,
  "fill_material": 0,
  "ok": 1
}